gyan/__init__.py
gyan-0.0.0.dist-info/METADATA
gyan-0.0.0.dist-info/RECORD
gyan-0.0.0.dist-info/WHEEL
gyan-0.0.0.dist-info/pbr.json
gyan-0.0.0.dist-info/top_level.txt
