Metadata-Version: 2.1
Name: gyan
Version: 0.0.0
Summary: Machine Learning Infrastructure on Openstack
Home-page: https://launchpad.net/gyan
Author: OpenStack
Author-email: openstack-dev@lists.openstack.org
License: UNKNOWN
Platform: UNKNOWN
Classifier: Environment :: OpenStack
Classifier: Intended Audience :: Information Technology
Classifier: Intended Audience :: System Administrators
Classifier: License :: OSI Approved :: Apache Software License
Classifier: Operating System :: POSIX :: Linux
Classifier: Programming Language :: Python
Classifier: Programming Language :: Python :: 2
Classifier: Programming Language :: Python :: 2.7
Classifier: Programming Language :: Python :: 3.5
Requires-Dist: pbr (>=1.6)
Requires-Dist: alembic (>=0.8.4)
Requires-Dist: Babel (>=2.3.4)
Requires-Dist: eventlet (!=0.18.3,>=0.18.2)
Requires-Dist: greenlet (>=0.3.2)
Requires-Dist: lxml (>=2.3)
Requires-Dist: netaddr (!=0.7.16,>=0.7.13)
Requires-Dist: oslo.config (>=3.14.0)
Requires-Dist: oslo.context (>=2.9.0)
Requires-Dist: oslo.db (!=4.13.1,!=4.13.2,>=4.10.0)
Requires-Dist: oslo.i18n (>=2.1.0)
Requires-Dist: oslo.log (>=3.22.0)
Requires-Dist: oslo.messaging (>=5.2.0)
Requires-Dist: oslo.middleware (>=3.0.0)
Requires-Dist: oslo.policy (>=1.9.0)
Requires-Dist: oslo.rootwrap (>=5.0.0)
Requires-Dist: oslo.serialization (>=1.10.0)
Requires-Dist: oslo.service (>=1.10.0)
Requires-Dist: oslo.utils (>=3.16.0)
Requires-Dist: oslo.concurrency (>=3.8.0)
Requires-Dist: osprofiler (>=1.4.0)
Requires-Dist: paramiko (>=2.0)
Requires-Dist: Paste
Requires-Dist: PasteDeploy (>=1.5.0)
Requires-Dist: pyparsing (>=2.0.1)
Requires-Dist: python-neutronclient (>=5.1.0)
Requires-Dist: keystoneauth1 (>=2.10.0)
Requires-Dist: keystonemiddleware (!=4.5.0,>=4.2.0)
Requires-Dist: requests (>=2.10.0)
Requires-Dist: retrying (!=1.3.0,>=1.2.3)
Requires-Dist: six (>=1.9.0)
Requires-Dist: SQLAlchemy (!=1.1.5,!=1.1.6,!=1.1.7,!=1.1.8,>=1.0.10)
Requires-Dist: stevedore (>=1.16.0)
Requires-Dist: python-cinderclient (>=2.0.1)
Requires-Dist: python-novaclient (>=7.1.0)
Requires-Dist: python-saharaclient (>=0.14.0)
Requires-Dist: WebOb (>=1.2.3)
Requires-Dist: Routes (!=2.0,!=2.3.0,>=1.12.3); (python_version!='2.7')
Requires-Dist: Routes (!=2.0,!=2.1,!=2.3.0,>=1.12.3); (python_version=='2.7')
